README.md
git-multi
git-old-branches
git-recent
git-relation
git-semver
setup.py
git_plus.egg-info/PKG-INFO
git_plus.egg-info/SOURCES.txt
git_plus.egg-info/dependency_links.txt
git_plus.egg-info/top_level.txt
gitplus/__init__.py
gitplus/cmd_git_multi.py
gitplus/cmd_git_old_branches.py
gitplus/cmd_git_recent.py
gitplus/cmd_git_relation.py
gitplus/cmd_git_semver.py
gitplus/git.py
gitplus/semver.py
gitplus/utils.py