Metadata-Version: 1.1
Name: git-plus
Version: 0.4.8
Summary: Set of git utilities
Home-page: https://github.com/tkrajina/git-plus
Author: Tomo Krajina
Author-email: tkrajina@gmail.com
License: Apache License, Version 2.0
Platform: UNKNOWN
Classifier: Programming Language :: Python
Classifier: Programming Language :: Python :: 3
